vutime_pkg/__init__.py
vutime_pkg/conversions/__init__.py
vutime_pkg/conversions/retrieve_tzs.py
vutime_pkg/conversions/timezones.py
vutime_pkg/operations/__init__.py
vutime_pkg/operations/add.py
vutime_pkg/operations/subtract.py
vutime-0.2.1.dist-info/METADATA
vutime-0.2.1.dist-info/WHEEL
vutime-0.2.1.dist-info/top_level.txt
vutime-0.2.1.dist-info/RECORD
