Metadata-Version: 2.4
Name: vutime
Version: 0.2.1
Summary: Time Based Utility Tools
Author: WMI Dev Team
Classifier: Development Status :: 3 - Alpha
Classifier: Intended Audience :: Developers
Classifier: Programming Language :: Python :: 3
Classifier: Programming Language :: Python :: 3.12
Requires-Python: >=3.12
Requires-Dist: beautifulsoup4
Requires-Dist: requests
